epicas/__init__.py
epicas/blocks/__init__.py
epicas/blocks/arima.py
epicas/blocks/attention.py
epicas/blocks/input.py
epicas/blocks/sequence.py
epicas/core/__init__.py
epicas/core/wrapper.py
epicas/preprocessor/__init__.py
epicas/preprocessor/engine.py
epicas/preprocessor/reader.py
epicas/settings/__init__.py
epicas/settings/hyperparams.json
epicas/settings/settings.py
epicas/utils/__init__.py
epicas/utils/data_helper.py
epicas-0.1.0.dist-info/LICENSE.txt
epicas-0.1.0.dist-info/METADATA
epicas-0.1.0.dist-info/WHEEL
epicas-0.1.0.dist-info/top_level.txt
epicas-0.1.0.dist-info/RECORD
